xmi/__init__.py
xmi_reader-0.5.9.dist-info/LICENSE
xmi_reader-0.5.9.dist-info/METADATA
xmi_reader-0.5.9.dist-info/WHEEL
xmi_reader-0.5.9.dist-info/top_level.txt
xmi_reader-0.5.9.dist-info/RECORD
