Metadata-Version: 2.1
Name: xmi-reader
Version: 0.5.9
Summary: Open and extract (unload) XMI/AWS/HET mainframe files.
Home-page: https://github.com/mainframed/xmi/
Author: Philip Young
Author-email: mainframed767@gmail.com
License: GPLv2
Project-URL: Bug Tracker, https://github.com/mainframed/xmi/issues
Platform: UNKNOWN
Classifier: Programming Language :: Python :: 3
Classifier: License :: OSI Approved :: GNU General Public License v2 (GPLv2)
Classifier: Operating System :: OS Independent
Requires-Dist: ebcdic
Requires-Dist: prettytable
Requires-Dist: python-magic
